geneticops/__init__.py
geneticops/ejemplos/__init__.py
geneticops/ejemplos/maximizar_funcion.py
geneticops/ejemplos/problema_mochila.py
geneticops/ejemplos/viajero_comercio.py
geneticops/geneticops/__init__.py
geneticops/geneticops/algoritmo.py
geneticops/geneticops/condiciones_parada.py
geneticops/geneticops/cruce.py
geneticops/geneticops/mutacion.py
geneticops/geneticops/poblacion.py
geneticops/geneticops/reemplazo.py
geneticops/geneticops/seleccion.py
geneticops/geneticops/utilidades.py
geneticops/tests/__init__.py
geneticops/tests/test_algoritmo.py
geneticops/tests/test_condiciones_parada.py
geneticops/tests/test_cruce.py
geneticops/tests/test_mutacion.py
geneticops/tests/test_poblacion.py
geneticops/tests/test_reemplazo.py
geneticops/tests/test_seleccion.py
geneticops/tests/test_utilidades.py
geneticops-0.1.0.dist-info/licenses/LICENSE
geneticops-0.1.0.dist-info/METADATA
geneticops-0.1.0.dist-info/WHEEL
geneticops-0.1.0.dist-info/top_level.txt
geneticops-0.1.0.dist-info/RECORD
