Metadata-Version: 2.4
Name: geneticops
Version: 0.1.0
Summary: Librería de algoritmos genéticos en Python
Author: Juan David Moreno Beltran
Author-email: jdmoreno@gmail.com
Requires-Python: >=3.6
License-File: LICENSE
Requires-Dist: numpy>=1.18.0
Requires-Dist: matplotlib>=3.3.0
Dynamic: author
Dynamic: author-email
Dynamic: description
Dynamic: description-content-type
Dynamic: license-file
Dynamic: requires-dist
Dynamic: requires-python
Dynamic: summary
